pgctl/__init__.py
pgctl/__main__.py
pgctl/cli.py
pgctl/config.py
pgctl/configsearch.py
pgctl/daemontools.py
pgctl/debug.py
pgctl/environment_tracing.py
pgctl/errors.py
pgctl/flock.py
pgctl/functions.py
pgctl/fuser.py
pgctl/log_viewer.py
pgctl/poll_ready.py
pgctl/service.py
pgctl/subprocess.py
pgctl/telemetry.py
pgctl-5.2.1.dist-info/COPYING
pgctl-5.2.1.dist-info/METADATA
pgctl-5.2.1.dist-info/WHEEL
pgctl-5.2.1.dist-info/entry_points.txt
pgctl-5.2.1.dist-info/top_level.txt
pgctl-5.2.1.dist-info/RECORD
