Metadata-Version: 2.1
Name: pgctl
Version: 5.2.1
Summary: A tool to configure and manage developer playgrounds.
Home-page: http://pgctl.readthedocs.org/en/latest/
Author: Buck Evan
Author-email: buck.2019@gmail.com
License: UNKNOWN
Platform: linux
Classifier: License :: OSI Approved :: MIT License
Classifier: Programming Language :: Python :: 3
Classifier: Programming Language :: Python :: 3.6
Classifier: Programming Language :: Python :: 3.7
Classifier: Programming Language :: Python :: Implementation :: CPython
Requires-Python: >=3.6
Requires-Dist: frozendict
Requires-Dist: cached-property
Requires-Dist: contextlib2
Requires-Dist: py (>=1.4.32)
Requires-Dist: pyyaml
Requires-Dist: s6
Provides-Extra: telemetry
Requires-Dist: yelp-clog ; extra == 'telemetry'
